bmp-0.2.6.dist-info/METADATA
bmp-0.2.6.dist-info/WHEEL
bmp-0.2.6.dist-info/entry_points.txt
bmp/__init__.py
bmp/_bmp.cp310-win_amd64.pyd
bmp/pt_docs/api.rst
bmp/pt_docs/index.rst
bmp/pyterrier.py
bmp-0.2.6.dist-info/RECORD
