Metadata-Version: 2.4
Name: bmp
Version: 0.2.6
Classifier: Development Status :: 4 - Beta
Classifier: Intended Audience :: Developers
Classifier: Intended Audience :: Science/Research
Classifier: License :: OSI Approved :: Apache Software License
Classifier: Operating System :: OS Independent
Classifier: Programming Language :: Rust
Classifier: Programming Language :: Python :: Implementation :: CPython
Classifier: Programming Language :: Python :: Implementation :: PyPy
Classifier: Programming Language :: Python :: 3
Classifier: Programming Language :: Python :: 3.8
Classifier: Programming Language :: Python :: 3.9
Classifier: Programming Language :: Python :: 3.10
Classifier: Programming Language :: Python :: 3.11
Classifier: Programming Language :: Python :: 3.12
Classifier: Topic :: Scientific/Engineering :: Information Analysis
Classifier: Topic :: Text Processing :: Indexing
Requires-Dist: python-terrier ; extra == 'pyterrier'
Requires-Dist: pyterrier-alpha ; extra == 'pyterrier'
Provides-Extra: pyterrier
Summary: Faster Learned Sparse Retrieval with Block-Max Pruning
Keywords: information retrieval,sparse retrieval,search,indexing,block-max pruning
Author: Antonio Mallia, Torsten Suel, Nicola Tonellotto, Sean MacAvaney
License: Apache-2.0
Requires-Python: >=3.7
Project-URL: Homepage, https://github.com/pisa-engine/BMP
Project-URL: Repository, https://github.com/pisa-engine/BMP.git
Project-URL: Documentation, https://github.com/pisa-engine/BMP/tree/main/python
Project-URL: Bug Tracker, https://github.com/pisa-engine/BMP/issues
